{
  "id": "2025-09-10T20:00:00Z-fourtwentyanalytics-broadcast-seed",
  "ts_utc": "2025-09-10T20:00:00Z",
  "date": "2025-09-10",
  "module": "FourTwentyAnalytics",
  "repo": "fourtwentyanalytics",
  "title": "Master star broadcast seed initialized",
  "summary": "Bootstrapped constellation broadcasting: schema, nightly pulse, and Signal renderer.",
  "tags": ["broadcasting", "schema", "renderer", "pulse"],
  "rating": "high",
  "origin": {
    "name": "FourTwenty Analytics",
    "url": "https://zbreeden.github.io/FourTwentyAnalytics/",
    "emoji": "🔘"
  },
  "links": {
    "readme": "https://github.com/zbreeden/fourtwentyanalytics#readme",
    "page": "https://zbreeden.github.io/fourtwentyanalytics/",
    "data": "https://github.com/zbreeden/fourtwentyanalytics/tree/main/signals",
    "runbook": "https://github.com/zbreeden/fourtwentyanalytics/blob/main/RUNBOOK.md"
  },
  "payload": {
    "notes": "This is the top-level aggregator in FourTwentyAnalytics. Nightly pulse pulls latest.json from each star."
  },
  "checksum": "",
  "version": "1.0.0"
}
